LICENSE
MANIFEST.in
README.md
pyproject.toml
setup.cfg
setup.py
versioneer.py
docs/LICENSE.BOTNET
docs/LICENSE.EFFNETV2
docs/LICENSE.SWIN
docs/LICENSE.XCIT
src/openpifpaf_extras/__init__.py
src/openpifpaf_extras/_version.py
src/openpifpaf_extras.egg-info/PKG-INFO
src/openpifpaf_extras.egg-info/SOURCES.txt
src/openpifpaf_extras.egg-info/dependency_links.txt
src/openpifpaf_extras.egg-info/not-zip-safe
src/openpifpaf_extras.egg-info/requires.txt
src/openpifpaf_extras.egg-info/top_level.txt
src/openpifpaf_extras/network/__init__.py
src/openpifpaf_extras/network/basenetworks.py
src/openpifpaf_extras/network/bottleneck_transformer.py
src/openpifpaf_extras/network/effnetv2.py
src/openpifpaf_extras/network/swin_transformer.py
src/openpifpaf_extras/network/xcit.py