Metadata-Version: 2.1
Name: openpifpaf-extras
Version: 0.0.3
Summary: Extensions to OpenPifPaf
Home-page: https://github.com/openpifpaf/openpifpaf_extras
Author: Sven Kreiss
Author-email: research@svenkreiss.com
License: UNKNOWN
Platform: UNKNOWN
Requires-Python: >=3.7
Provides-Extra: dev
Provides-Extra: test
